[{"count":193905,"player_id":"13411"},{"count":143544,"player_id":"13296"},{"count":115325,"player_id":"13324"},{"count":90352,"player_id":"13424"},{"count":88416,"player_id":"13306"},{"count":72504,"player_id":"13348"},{"count":59823,"player_id":"13392"},{"count":57681,"player_id":"13401"},{"count":55881,"player_id":"13421"},{"count":55827,"player_id":"8180"},{"count":53370,"player_id":"13413"},{"count":46755,"player_id":"13400"},{"count":45577,"player_id":"8161"},{"count":43389,"player_id":"13403"},{"count":41690,"player_id":"13420"},{"count":41136,"player_id":"13335"},{"count":40266,"player_id":"13303"},{"count":36617,"player_id":"13414"},{"count":35413,"player_id":"13322"},{"count":34796,"player_id":"13434"},{"count":32116,"player_id":"13302"},{"count":31300,"player_id":"13307"},{"count":30156,"player_id":"13319"},{"count":29848,"player_id":"4017"},{"count":29376,"player_id":"13427"},{"count":25485,"player_id":"13282"},{"count":25344,"player_id":"13270"},{"count":24808,"player_id":"8117"},{"count":23430,"player_id":"13300"},{"count":22768,"player_id":"11783"},{"count":22687,"player_id":"13418"},{"count":22464,"player_id":"13289"},{"count":22422,"player_id":"13477"},{"count":22098,"player_id":"13329"},{"count":22005,"player_id":"13435"},{"count":18200,"player_id":"13404"},{"count":18018,"player_id":"9511"},{"count":17337,"player_id":"13408"},{"count":16794,"player_id":"10219"},{"count":16758,"player_id":"11581"},{"count":16362,"player_id":"13333"},{"count":14768,"player_id":"8172"},{"count":14571,"player_id":"13533"},{"count":14274,"player_id":"13423"},{"count":13945,"player_id":"8698"},{"count":13064,"player_id":"4033"},{"count":12579,"player_id":"13342"},{"count":12324,"player_id":"13278"},{"count":11990,"player_id":"13402"},{"count":11112,"player_id":"11610"},{"count":10215,"player_id":"11435"},{"count":10032,"player_id":"13354"},{"count":9494,"player_id":"13380"},{"count":9102,"player_id":"827"},{"count":8955,"player_id":"10226"},{"count":8722,"player_id":"12502"},{"count":8532,"player_id":"4993"},{"count":8456,"player_id":"12544"},{"count":8224,"player_id":"13338"},{"count":8136,"player_id":"1166"},{"count":7875,"player_id":"19"},{"count":7776,"player_id":"13317"},{"count":7728,"player_id":"3321"},{"count":7692,"player_id":"6865"},{"count":7416,"player_id":"5995"},{"count":7407,"player_id":"9506"},{"count":7293,"player_id":"13347"},{"count":7104,"player_id":"96"},{"count":7080,"player_id":"7528"},{"count":6876,"player_id":"9482"},{"count":6750,"player_id":"11571"},{"count":6741,"player_id":"9225"},{"count":6650,"player_id":"7049"},{"count":6632,"player_id":"9502"},{"count":6495,"player_id":"9479"},{"count":6464,"player_id":"12467"},{"count":6368,"player_id":"13320"},{"count":6336,"player_id":"1373"},{"count":6264,"player_id":"12540"},{"count":6228,"player_id":"8800"},{"count":6210,"player_id":"9487"},{"count":6146,"player_id":"8188"},{"count":5824,"player_id":"13394"},{"count":5730,"player_id":"6149"},{"count":5688,"player_id":"12641"},{"count":5679,"player_id":"6826"},{"count":5656,"player_id":"13299"},{"count":5628,"player_id":"11834"},{"count":5568,"player_id":"13600"},{"count":5544,"player_id":"12457"},{"count":5517,"player_id":"2505"},{"count":5499,"player_id":"13419"},{"count":5412,"player_id":"8111"},{"count":5376,"player_id":"12860"},{"count":5373,"player_id":"9494"},{"count":5346,"player_id":"12718"},{"count":5190,"player_id":"13285"},{"count":5139,"player_id":"7090"},{"count":5118,"player_id":"13416"},{"count":4944,"player_id":"8119"}]