[{"count":1720170,"player_id":"6865"},{"count":1433544,"player_id":"7607"},{"count":1063860,"player_id":"NO"},{"count":985284,"player_id":"2505"},{"count":953997,"player_id":"11579"},{"count":912816,"player_id":"10222"},{"count":695331,"player_id":"12500"},{"count":654305,"player_id":"MIN"},{"count":639900,"player_id":"11435"},{"count":619812,"player_id":"8800"},{"count":448060,"player_id":"6011"},{"count":381928,"player_id":"11625"},{"count":369460,"player_id":"9220"},{"count":368977,"player_id":"NE"},{"count":363632,"player_id":"12545"},{"count":338760,"player_id":"7611"},{"count":326214,"player_id":"9758"},{"count":322776,"player_id":"DET"},{"count":321444,"player_id":"12533"},{"count":311352,"player_id":"5230"},{"count":240926,"player_id":"7553"},{"count":233388,"player_id":"9487"},{"count":212361,"player_id":"5189"},{"count":191709,"player_id":"11624"},{"count":181800,"player_id":"12472"},{"count":167728,"player_id":"1166"},{"count":166145,"player_id":"4195"},{"count":165140,"player_id":"5967"},{"count":162826,"player_id":"11646"},{"count":157703,"player_id":"BUF"},{"count":152670,"player_id":"11608"},{"count":150723,"player_id":"12718"},{"count":143960,"player_id":"12519"},{"count":143384,"player_id":"7567"},{"count":142748,"player_id":"2216"},{"count":142062,"player_id":"5906"},{"count":137116,"player_id":"8161"},{"count":136989,"player_id":"9480"},{"count":134622,"player_id":"8180"},{"count":134144,"player_id":"4983"},{"count":130776,"player_id":"11539"},{"count":129792,"player_id":"11586"},{"count":129475,"player_id":"HOU"},{"count":122724,"player_id":"96"},{"count":121770,"player_id":"10232"},{"count":119340,"player_id":"4037"},{"count":115496,"player_id":"8183"},{"count":112832,"player_id":"4035"},{"count":111040,"player_id":"12538"},{"count":110490,"player_id":"12493"},{"count":109959,"player_id":"11565"},{"count":98298,"player_id":"10219"},{"count":97779,"player_id":"12517"},{"count":96430,"player_id":"TB"},{"count":95389,"player_id":"9754"},{"count":91658,"player_id":"3451"},{"count":90005,"player_id":"12469"},{"count":89452,"player_id":"331"},{"count":88606,"player_id":"4381"},{"count":86646,"player_id":"7049"},{"count":83135,"player_id":"6271"},{"count":76032,"player_id":"8205"},{"count":74226,"player_id":"4177"},{"count":73400,"player_id":"6650"},{"count":71298,"player_id":"11560"},{"count":67533,"player_id":"SF"},{"count":66972,"player_id":"JAX"},{"count":66920,"player_id":"11439"},{"count":64278,"player_id":"11603"},{"count":63720,"player_id":"2307"},{"count":63640,"player_id":"8121"},{"count":62860,"player_id":"11638"},{"count":60666,"player_id":"PIT"},{"count":59780,"player_id":"12506"},{"count":58496,"player_id":"9228"},{"count":57834,"player_id":"11563"},{"count":53580,"player_id":"12534"},{"count":52736,"player_id":"1479"},{"count":51088,"player_id":"11655"},{"count":50640,"player_id":"NYG"},{"count":48546,"player_id":"12484"},{"count":46836,"player_id":"4147"},{"count":44886,"player_id":"6770"},{"count":44860,"player_id":"8408"},{"count":44523,"player_id":"9511"},{"count":43616,"player_id":"12492"},{"count":41888,"player_id":"9225"},{"count":39056,"player_id":"11783"},{"count":38805,"player_id":"11627"},{"count":38520,"player_id":"1945"},{"count":37704,"player_id":"8154"},{"count":37495,"player_id":"11647"},{"count":35775,"player_id":"9500"},{"count":35604,"player_id":"421"},{"count":34840,"player_id":"4233"},{"count":34802,"player_id":"5022"},{"count":34695,"player_id":"5045"},{"count":34565,"player_id":"12503"},{"count":34071,"player_id":"11792"},{"count":33649,"player_id":"12502"}]